ipyniivue_experimental/__init__.py
ipyniivue_experimental/static/widget_send.css
ipyniivue_experimental/static/widget_send.js
ipyniivue_experimental/static/widget_traitlet.css
ipyniivue_experimental/static/widget_traitlet.js
ipyniivue_experimental-0.0.6.dist-info/METADATA
ipyniivue_experimental-0.0.6.dist-info/WHEEL
ipyniivue_experimental-0.0.6.dist-info/licenses/LICENSE
ipyniivue_experimental-0.0.6.dist-info/RECORD
