Metadata-Version: 2.1
Name: ipyniivue_experimental
Version: 0.0.6
License-File: LICENSE
Requires-Dist: anywidget
Provides-Extra: dev
Requires-Dist: jupyterlab; extra == 'dev'
Requires-Dist: watchfiles; extra == 'dev'
